Workbook

Sheet Invoice
A1: TAX INVOICE
A2: =IF(OR(B47="COMPOSITION",LEFT(B46,11)="Composition"),"BILL OF SUPPLY | Composition Scheme","TAX INVOICE | Regular Taxation") -> TAX INVOICE | Regular Taxation
A4: GST RATE PRESET (select once — all tax logic updates automatically)
A5: Select Preset → | B5: Regular 18% (Inter-State IGST)
A6: Scheme | B6: =IFERROR(VLOOKUP(B5,Masters!$A$20:$E$31,2,FALSE()),"REGULAR") -> REGULAR | C6: CGST % | D6: =IFERROR(VLOOKUP(B5,Masters!$A$20:$E$31,3,FALSE()),0) -> 0 | E6: SGST % | F6: =IFERROR(VLOOKUP(B5,Masters!$A$20:$E$31,4,FALSE()),0) -> 0 | G6: IGST % | H6: =IFERROR(VLOOKUP(B5,Masters!$A$20:$E$31,5,FALSE()),0) -> 0.18
A8: SUPPLIER | E8: RECIPIENT / BILL TO
A9: =BusinessDetails!B5 -> Apex Consulting Group | E9: =BusinessDetails!B22 -> Meridian Technologies Pvt. Ltd.
A10: ="GSTIN: "&BusinessDetails!B6&" | PAN: "&BusinessDetails!B7 -> GSTIN: 27AABCA1234D1Z5 | PAN: AABCA1234D | E10: ="GSTIN: "&BusinessDetails!B23&" | PAN: "&BusinessDetails!B24 -> GSTIN: 33AADCM9876K1Z2 | PAN: AADCM9876K
A11: ="State: "&BusinessDetails!B8&"-"&BusinessDetails!B9 -> State: 27-Maharashtra | E11: ="State: "&BusinessDetails!B25&"-"&BusinessDetails!B26 -> State: 33-Tamil Nadu
A12: =BusinessDetails!B10 -> 12th Floor, One World Centre, Senapati Bapat Marg | E12: =BusinessDetails!B27 -> No. 42, Rajiv Gandhi Salai (OMR)
A13: =BusinessDetails!B11 -> Lower Parel, Mumbai, Maharashtra 400013 | E13: =BusinessDetails!B28 -> Thoraipakkam, Chennai, Tamil Nadu 600097
A14: ="Tel: "&BusinessDetails!B12&" | "&BusinessDetails!B13 -> Tel: +91 22 6123 4500 | billing@apexconsulting.in | E14: ="Attn: "&BusinessDetails!B29 -> Attn: Accounts Payable
A16: Invoice No: | B16: =BusinessDetails!B32 -> INV-2026-0918 | C16: Date: | D16: =BusinessDetails!B33 -> 18-Sep-2026 | E16: Due: | F16: =BusinessDetails!B34 -> 18-Oct-2026 | G16: PO: | H16: =BusinessDetails!B35 -> PO-88421-A
A17: Place of Supply: | B17: =BusinessDetails!B25&"-"&BusinessDetails!B26 -> 33-Tamil Nadu | D17: Supply Type: | E17: =IF(BusinessDetails!B8=BusinessDetails!B25,"Intra-State","Inter-State") -> Inter-State | F17: Reverse Charge: | G17: =BusinessDetails!B36 -> No
A19: LINE ITEMS — Select service/product from dropdown (or CUSTOM). Only Qty is entered; all else auto-fills.
A20: # | B20: Service / Product (select) | C20: SAC/HSN | D20: Qty | E20: Unit | F20: Rate (₹) | G20: Amount (₹) | H20: Mode
A21: 1 | B21: Enterprise Cloud Migration Assessment | C21: =IF(B21="","",IF(B21="<< CUSTOM ENTRY >>","",IFERROR(INDEX(Masters!$D$5:$D$15,MATCH(B21,Masters!$B$5:$B$15,0)),""))) -> 998311 | D21: 1 | E21: =IF(B21="","",IF(B21="<< CUSTOM ENTRY >>","",IFERROR(INDEX(Masters!$E$5:$E$15,MATCH(B21,Masters!$B$5:$B$15,0)),""))) -> Project | F21: =IF(B21="","",IF(B21="<< CUSTOM ENTRY >>",0,IFERROR(INDEX(Masters!$F$5:$F$15,MATCH(B21,Masters!$B$5:$B$15,0)),0))) -> 18500 | G21: =IF(OR(B21="",D21=""),"",ROUND(D21*F21,2)) -> 18500 | H21: =IF(B21="","",IF(B21="<< CUSTOM ENTRY >>","Custom","Catalog")) -> Catalog
A22: 2 | B22: Security & Compliance Review | C22: =IF(B22="","",IF(B22="<< CUSTOM ENTRY >>","",IFERROR(INDEX(Masters!$D$5:$D$15,MATCH(B22,Masters!$B$5:$B$15,0)),""))) -> 998311 | D22: 80 | E22: =IF(B22="","",IF(B22="<< CUSTOM ENTRY >>","",IFERROR(INDEX(Masters!$E$5:$E$15,MATCH(B22,Masters!$B$5:$B$15,0)),""))) -> Hours | F22: =IF(B22="","",IF(B22="<< CUSTOM ENTRY >>",0,IFERROR(INDEX(Masters!$F$5:$F$15,MATCH(B22,Masters!$B$5:$B$15,0)),0))) -> 180 | G22: =IF(OR(B22="",D22=""),"",ROUND(D22*F22,2)) -> 14400 | H22: =IF(B22="","",IF(B22="<< CUSTOM ENTRY >>","Custom","Catalog")) -> Catalog
A23: 3 | B23: Data Architecture Design Workshop | C23: =IF(B23="","",IF(B23="<< CUSTOM ENTRY >>","",IFERROR(INDEX(Masters!$D$5:$D$15,MATCH(B23,Masters!$B$5:$B$15,0)),""))) -> 998311 | D23: 3 | E23: =IF(B23="","",IF(B23="<< CUSTOM ENTRY >>","",IFERROR(INDEX(Masters!$E$5:$E$15,MATCH(B23,Masters!$B$5:$B$15,0)),""))) -> Days | F23: =IF(B23="","",IF(B23="<< CUSTOM ENTRY >>",0,IFERROR(INDEX(Masters!$F$5:$F$15,MATCH(B23,Masters!$B$5:$B$15,0)),0))) -> 3250 | G23: =IF(OR(B23="",D23=""),"",ROUND(D23*F23,2)) -> 9750 | H23: =IF(B23="","",IF(B23="<< CUSTOM ENTRY >>","Custom","Catalog")) -> Catalog
A24: 4 | B24: Implementation Support Retainer | C24: =IF(B24="","",IF(B24="<< CUSTOM ENTRY >>","",IFERROR(INDEX(Masters!$D$5:$D$15,MATCH(B24,Masters!$B$5:$B$15,0)),""))) -> 998314 | D24: 3 | E24: =IF(B24="","",IF(B24="<< CUSTOM ENTRY >>","",IFERROR(INDEX(Masters!$E$5:$E$15,MATCH(B24,Masters!$B$5:$B$15,0)),""))) -> Months | F24: =IF(B24="","",IF(B24="<< CUSTOM ENTRY >>",0,IFERROR(INDEX(Masters!$F$5:$F$15,MATCH(B24,Masters!$B$5:$B$15,0)),0))) -> 4000 | G24: =IF(OR(B24="",D24=""),"",ROUND(D24*F24,2)) -> 12000 | H24: =IF(B24="","",IF(B24="<< CUSTOM ENTRY >>","Custom","Catalog")) -> Catalog
A25: 5 | C25: =IF(B25="","",IF(B25="<< CUSTOM ENTRY >>","",IFERROR(INDEX(Masters!$D$5:$D$15,MATCH(B25,Masters!$B$5:$B$15,0)),""))) | E25: =IF(B25="","",IF(B25="<< CUSTOM ENTRY >>","",IFERROR(INDEX(Masters!$E$5:$E$15,MATCH(B25,Masters!$B$5:$B$15,0)),""))) | F25: =IF(B25="","",IF(B25="<< CUSTOM ENTRY >>",0,IFERROR(INDEX(Masters!$F$5:$F$15,MATCH(B25,Masters!$B$5:$B$15,0)),0))) | G25: =IF(OR(B25="",D25=""),"",ROUND(D25*F25,2)) | H25: =IF(B25="","",IF(B25="<< CUSTOM ENTRY >>","Custom","Catalog"))
A26: 6 | C26: =IF(B26="","",IF(B26="<< CUSTOM ENTRY >>","",IFERROR(INDEX(Masters!$D$5:$D$15,MATCH(B26,Masters!$B$5:$B$15,0)),""))) | E26: =IF(B26="","",IF(B26="<< CUSTOM ENTRY >>","",IFERROR(INDEX(Masters!$E$5:$E$15,MATCH(B26,Masters!$B$5:$B$15,0)),""))) | F26: =IF(B26="","",IF(B26="<< CUSTOM ENTRY >>",0,IFERROR(INDEX(Masters!$F$5:$F$15,MATCH(B26,Masters!$B$5:$B$15,0)),0))) | G26: =IF(OR(B26="",D26=""),"",ROUND(D26*F26,2)) | H26: =IF(B26="","",IF(B26="<< CUSTOM ENTRY >>","Custom","Catalog"))
A27: 7 | C27: =IF(B27="","",IF(B27="<< CUSTOM ENTRY >>","",IFERROR(INDEX(Masters!$D$5:$D$15,MATCH(B27,Masters!$B$5:$B$15,0)),""))) | E27: =IF(B27="","",IF(B27="<< CUSTOM ENTRY >>","",IFERROR(INDEX(Masters!$E$5:$E$15,MATCH(B27,Masters!$B$5:$B$15,0)),""))) | F27: =IF(B27="","",IF(B27="<< CUSTOM ENTRY >>",0,IFERROR(INDEX(Masters!$F$5:$F$15,MATCH(B27,Masters!$B$5:$B$15,0)),0))) | G27: =IF(OR(B27="",D27=""),"",ROUND(D27*F27,2)) | H27: =IF(B27="","",IF(B27="<< CUSTOM ENTRY >>","Custom","Catalog"))
A28: 8 | C28: =IF(B28="","",IF(B28="<< CUSTOM ENTRY >>","",IFERROR(INDEX(Masters!$D$5:$D$15,MATCH(B28,Masters!$B$5:$B$15,0)),""))) | E28: =IF(B28="","",IF(B28="<< CUSTOM ENTRY >>","",IFERROR(INDEX(Masters!$E$5:$E$15,MATCH(B28,Masters!$B$5:$B$15,0)),""))) | F28: =IF(B28="","",IF(B28="<< CUSTOM ENTRY >>",0,IFERROR(INDEX(Masters!$F$5:$F$15,MATCH(B28,Masters!$B$5:$B$15,0)),0))) | G28: =IF(OR(B28="",D28=""),"",ROUND(D28*F28,2)) | H28: =IF(B28="","",IF(B28="<< CUSTOM ENTRY >>","Custom","Catalog"))
A29: CUSTOM MODE: Select "<< CUSTOM ENTRY >>" in Service column, then type SAC, Unit and Rate directly over the gray cells (replace formula). Qty remains the only required input for catalog items.
A31: BANK DETAILS | E31: Taxable Value | G31: =IFERROR(SUM(G21:G28),0) -> 54650
A32: =BusinessDetails!B14&" | A/c: "&BusinessDetails!B16 -> HDFC Bank Ltd. | A/c: 502000********21 | E32: CGST | F32: =D6 -> 0 | G32: =IF(B6="COMPOSITION",0,ROUND(G31*D6,2)) -> 0
A33: ="IFSC: "&BusinessDetails!B17&" | "&BusinessDetails!B18 -> IFSC: HDFC0000123 | Lower Parel, Mumbai | E33: SGST | F33: =F6 -> 0 | G33: =IF(B6="COMPOSITION",0,ROUND(G31*F6,2)) -> 0
A34: ="UPI: "&BusinessDetails!B19 -> UPI: apex.billing@hdfcbank | E34: IGST | F34: =H6 -> 0.18 | G34: =IF(B6="COMPOSITION",0,ROUND(G31*H6,2)) -> 9837
E35: Total Tax | G35: =G32+G33+G34 -> 9837
E36: GRAND TOTAL | G36: =G31+G35 -> 64487
A38: PAYMENT TERMS
A39: Payment due within 30 days (Net 30). Quote Invoice No. on remittance. Late payments attract interest @ 18% p.a. under MSMED Act if applicable. This document is generated under CGST/IGST Acts. All amounts in INR.
A42: AUTHORIZATION
A43: For Supplier: ____________________ Name / Title / Date | E43: For Recipient: ____________________ Name / Title / Date
A45: How to use: 1) Edit BusinessDetails sheet for names/addresses. 2) Select GST Rate Preset (B5). 3) Select services from dropdown in col B. 4) Enter Qty only. 5) For custom items select << CUSTOM ENTRY >> and overwrite SAC/Unit/Rate.
B46: =B6 -> REGULAR | D46: =D6 -> 0 | F46: =F6 -> 0 | H46: =H6 -> 0.18
B47: =B6 -> REGULAR

Sheet BusinessDetails
A1: EDITABLE BUSINESS DETAILS
A2: Yellow cells = edit these. Changes flow automatically to the Invoice sheet.
A4: SUPPLIER (Your Company)
A5: Company Name | B5: Apex Consulting Group
A6: GSTIN | B6: 27AABCA1234D1Z5
A7: PAN | B7: AABCA1234D
A8: State Code | B8: 27
A9: State Name | B9: Maharashtra
A10: Address Line 1 | B10: 12th Floor, One World Centre, Senapati Bapat Marg
A11: Address Line 2 | B11: Lower Parel, Mumbai, Maharashtra 400013
A12: Phone | B12: +91 22 6123 4500
A13: Email | B13: billing@apexconsulting.in
A14: Bank Name | B14: HDFC Bank Ltd.
A15: Account Name | B15: Apex Consulting Group
A16: Account No | B16: 502000********21
... A19: UPI | B19: apex.billing@hdfcbank
A21: RECIPIENT (Customer)
A22: Company Name | B22: Meridian Technologies Pvt. Ltd.
A23: GSTIN | B23: 33AADCM9876K1Z2
A24: PAN | B24: AADCM9876K
A25: State Code | B25: 33
A26: State Name | B26: Tamil Nadu
A27: Address Line 1 | B27: No. 42, Rajiv Gandhi Salai (OMR)
A28: Address Line 2 | B28: Thoraipakkam, Chennai, Tamil Nadu 600097
A29: Contact / Attn | B29: Accounts Payable
A31: INVOICE META (Editable)
A32: Invoice No | B32: INV-2026-0918
A33: Invoice Date | B33: 18-Sep-2026
A34: Due Date | B34: 18-Oct-2026
A35: PO / Reference | B35: PO-88421-A
A36: Reverse Charge | B36: No

Sheet Masters
A1: MASTERS — Do not delete rows. Add new services/products below.
A3: SERVICE / PRODUCT CATALOG
A4: Code | B4: Description | C4: Type | D4: SAC/HSN | E4: Unit | F4: Rate (₹) | G4: Active
A5: SVC-001 | B5: Enterprise Cloud Migration Assessment | C5: Service | D5: 998311 | E5: Project | F5: 18500 | G5: Yes
A6: SVC-002 | B6: Security & Compliance Review | C6: Service | D6: 998311 | E6: Hours | F6: 180 | G6: Yes
A7: SVC-003 | B7: Data Architecture Design Workshop | C7: Service | D7: 998311 | E7: Days | F7: 3250 | G7: Yes
A8: SVC-004 | B8: Implementation Support Retainer | C8: Service | D8: 998314 | E8: Months | F8: 4000 | G8: Yes
A9: SVC-005 | B9: IT Infrastructure Audit | C9: Service | D9: 998311 | E9: Project | F9: 12500 | G9: Yes
A10: SVC-006 | B10: Cloud Cost Optimization | C10: Service | D10: 998311 | E10: Project | F10: 9800 | G10: Yes
A11: SVC-007 | B11: DevOps Pipeline Setup | C11: Service | D11: 998314 | E11: Project | F11: 15000 | G11: Yes
A12: SVC-008 | B12: Managed Support (Monthly) | C12: Service | D12: 998314 | E12: Months | F12: 3500 | G12: Yes
A13: PRD-001 | B13: Software License - Enterprise | C13: Product | D13: 8523 | E13: License | F13: 45000 | G13: Yes
A14: PRD-002 | B14: Hardware Appliance - Firewall | C14: Product | D14: 8517 | E14: Unit | F14: 85000 | G14: Yes
A15: CUSTOM | B15: << CUSTOM ENTRY >> | C15: Custom | E15: Unit | F15: 0 | G15: Yes
A18: GST RATE PRESETS (click one on Invoice sheet — single selection drives all tax logic)
A19: Preset Name | B19: Scheme | C19: CGST % | D19: SGST % | E19: IGST %
A20: Regular 18% (Inter-State IGST) | B20: REGULAR | C20: 0 | D20: 0 | E20: 0.18
A21: Regular 18% (Intra-State CGST+SGST) | B21: REGULAR | C21: 0.09 | D21: 0.09 | E21: 0
A22: Regular 12% (Inter-State IGST) | B22: REGULAR | C22: 0 | D22: 0 | E22: 0.12
A23: Regular 12% (Intra-State CGST+SGST) | B23: REGULAR | C23: 0.06 | D23: 0.06 | E23: 0
A24: Regular 5% (Inter-State IGST) | B24: REGULAR | C24: 0 | D24: 0 | E24: 0.05
A25: Regular 5% (Intra-State CGST+SGST) | B25: REGULAR | C25: 0.025 | D25: 0.025 | E25: 0
A26: Regular 28% (Inter-State IGST) | B26: REGULAR | C26: 0 | D26: 0 | E26: 0.28
A27: Regular 28% (Intra-State CGST+SGST) | B27: REGULAR | C27: 0.14 | D27: 0.14 | E27: 0
A28: Composition 6% (Services) | B28: COMPOSITION | C28: 0 | D28: 0 | E28: 0
A29: Composition 1% (Traders) | B29: COMPOSITION | C29: 0 | D29: 0 | E29: 0
A30: Composition 5% (Restaurants) | B30: COMPOSITION | C30: 0 | D30: 0 | E30: 0
A31: Exempt / Nil Rated | B31: REGULAR | C31: 0 | D31: 0 | E31: 0
A34: Units list (for Custom mode)
A35: Project
A36: Hours
A37: Days
A38: Months
A39: Unit
A40: License
A41: Nos
A42: Kg
A43: Litre
A44: Set

Sheet Instructions
A1: HOW TO USE THIS GST INVOICE WORKBOOK
A4: 1. BUSINESS DETAILS (Sheet: BusinessDetails)
A5: • Edit all yellow cells: company name, GSTIN, address, bank, customer details, invoice number/dates.
A6: • Changes automatically appear on the Invoice sheet.
A8: 2. GST RATE PRESET (Invoice sheet, cell B5) — SINGLE CLICK
A9: • Click the yellow cell B5 and pick a preset from the dropdown.
A10: • Options cover Regular 5%/12%/18%/28% (Inter-State IGST or Intra-State CGST+SGST),
A11: Composition schemes (6%/1%/5%), and Exempt.
A12: • Selecting a preset auto-updates Scheme, CGST%, SGST%, IGST% and recalculates all tax lines.
A13: • Composition → document becomes Bill of Supply; no GST charged to customer.
A15: 3. LINE ITEMS (Invoice sheet)
A16: • Column B (Service/Product): dropdown list from Masters catalog. Select an item.
... A40: • Hide Masters / BusinessDetails / Instructions before sharing if desired.
